kong_pluginserver/__init__.py
kong_pluginserver/cli.py
kong_pluginserver/const.py
kong_pluginserver/exception.py
kong_pluginserver/logger.py
kong_pluginserver/module.py
kong_pluginserver/pdk.py
kong_pluginserver/server.py
kong_pluginserver-0.12.dist-info/LICENSE
kong_pluginserver-0.12.dist-info/METADATA
kong_pluginserver-0.12.dist-info/WHEEL
kong_pluginserver-0.12.dist-info/entry_points.txt
kong_pluginserver-0.12.dist-info/top_level.txt
kong_pluginserver-0.12.dist-info/RECORD
