Metadata-Version: 2.1
Name: kong_pluginserver
Version: 0.12
Summary: Kong Python Plugin Server
Home-page: https://github.com/fffonion/kong-python-pluginserver
Author: fffonion
Author-email: fffonion@gmail.com
License: GPLv3
Platform: UNKNOWN
Classifier: License :: OSI Approved :: BSD License
Classifier: Programming Language :: Python
Classifier: Programming Language :: Python :: 2.7
Classifier: Programming Language :: Python :: 3
Classifier: Programming Language :: Python :: 3.6
Classifier: Programming Language :: Python :: 3.7
Classifier: Programming Language :: Python :: Implementation :: CPython
Requires: gevent
Requires: msgpack
